<?xml version="1.0"?>
<DescriptorRecordSet LanguageCode="eng">
	<DescriptorRecord DescriptorClass="1">
		<DescriptorUI>D000007</DescriptorUI>
		<DescriptorName>
			<String>Abdominal Injuries</String>
		</DescriptorName>
		<DateCreated>
			<Year>1999</Year>
			<Month>01</Month>
			<Day>01</Day>
		</DateCreated>
		<DateRevised>
			<Year>2010</Year>
			<Month>06</Month>
			<Day>25</Day>
		</DateRevised>
		<ActiveMeSHYearList>
			<Year>2011</Year>
			<Year>2012</Year>
			<Year>2013</Year>
			<Year>2014</Year>
			<Year>2015</Year>
		</ActiveMeSHYearList>
		<AllowableQualifiersList>
			<AllowableQualifier>
				<QualifierReferredTo>
					<QualifierUI>Q000151</QualifierUI>
					<QualifierName>
						<String>congenital</String>
					</QualifierName>
				</QualifierReferredTo>
				<Abbreviation>CN</Abbreviation>
			</AllowableQualifier>
			<AllowableQualifier>
				<QualifierReferredTo>
					<QualifierUI>Q000134</QualifierUI>
					<QualifierName>
						<String>cerebrospinal fluid</String>
					</QualifierName>
				</QualifierReferredTo>
				<Abbreviation>CF</Abbreviation>
			</AllowableQualifier>
			<AllowableQualifier>
				<QualifierReferredTo>
					<QualifierUI>Q000139</QualifierUI>
					<QualifierName>
						<String>chemically induced</String>
					</QualifierName>
				</QualifierReferredTo>
				<Abbreviation>CI</Abbreviation>
			</AllowableQualifier>
			<AllowableQualifier>
				<QualifierReferredTo>
					<QualifierUI>Q000097</QualifierUI>
					<QualifierName>
						<String>blood</String>
					</QualifierName>
				</QualifierReferredTo>
				<Abbreviation>BL</Abbreviation>
			</AllowableQualifier>
		</AllowableQualifiersList>
		<TreeNumberList>
			<TreeNumber>C26.017</TreeNumber>
		</TreeNumberList>
		<RecordOriginatorsList>
			<RecordOriginator>nlm</RecordOriginator>
			<RecordMaintainer>chodan</RecordMaintainer>
			<RecordAuthorizer>nelsons</RecordAuthorizer>
		</RecordOriginatorsList>
		<ConceptList>
			<Concept PreferredConceptYN="Y">
				<ConceptUI>M0000007</ConceptUI>
				<ConceptName>
					<String>Abdominal Injuries</String>
				</ConceptName>
				<ScopeNote>General or unspecified injuries involving organs in the abdominal cavity.
    </ScopeNote>
				<SemanticTypeList>
					<SemanticType>
						<SemanticTypeUI>T037</SemanticTypeUI>
						<SemanticTypeName>Injury or Poisoning</SemanticTypeName>
					</SemanticType>
				</SemanticTypeList>
				<TermList>
					<Term ConceptPreferredTermYN="Y" IsPermutedTermYN="N" LexicalTag="NON" PrintFlagYN="Y" RecordPreferredTermYN="Y">
						<TermUI>T000015</TermUI>
						<String>Abdominal Injuries</String>
						<DateCreated>
							<Year>1999</Year>
							<Month>01</Month>
							<Day>01</Day>
						</DateCreated>
						<EntryVersion>ABDOMINAL INJ</EntryVersion>
						<ThesaurusIDlist>
							<ThesaurusID>NLM (1966)</ThesaurusID>
						</ThesaurusIDlist>
					</Term>
					<Term ConceptPreferredTermYN="N" IsPermutedTermYN="N" LexicalTag="NON" PrintFlagYN="N" RecordPreferredTermYN="N">
						<TermUI>T000014</TermUI>
						<String>Injuries, Abdominal</String>
						<DateCreated>
							<Year>1986</Year>
							<Month>01</Month>
							<Day>01</Day>
						</DateCreated>
						<EntryVersion>INJ ABDOMINAL</EntryVersion>
						<ThesaurusIDlist>
							<ThesaurusID>UNK (19XX)</ThesaurusID>
						</ThesaurusIDlist>
					</Term>
					<Term ConceptPreferredTermYN="N" IsPermutedTermYN="Y" LexicalTag="NON" PrintFlagYN="N" RecordPreferredTermYN="N">
						<TermUI>T000014</TermUI>
						<String>Abdominal Injury</String>
					</Term>
					<Term ConceptPreferredTermYN="N" IsPermutedTermYN="Y" LexicalTag="NON" PrintFlagYN="N" RecordPreferredTermYN="N">
						<TermUI>T000014</TermUI>
						<String>Injury, Abdominal</String>
					</Term>
				</TermList>
			</Concept>
		</ConceptList>
	</DescriptorRecord>
	<DescriptorRecord DescriptorClass="1">
		<DescriptorUI>D000008</DescriptorUI>
		<DescriptorName>
			<String>Abdominal Neoplasms</String>
		</DescriptorName>
		<DateCreated>
			<Year>1999</Year>
			<Month>01</Month>
			<Day>01</Day>
		</DateCreated>
		<DateRevised>
			<Year>1995</Year>
			<Month>06</Month>
			<Day>08</Day>
		</DateRevised>
		<ActiveMeSHYearList>
			<Year>1996</Year>
			<Year>1997</Year>
			<Year>1998</Year>
			<Year>1999</Year>
			<Year>2000</Year>
			<Year>2001</Year>
			<Year>2002</Year>
			<Year>2003</Year>
			<Year>2004</Year>
			<Year>2005</Year>
			<Year>2006</Year>
			<Year>2007</Year>
			<Year>2008</Year>
			<Year>2009</Year>
			<Year>2010</Year>
			<Year>2011</Year>
			<Year>2012</Year>
			<Year>2013</Year>
			<Year>2014</Year>
			<Year>2015</Year>
		</ActiveMeSHYearList>
		<AllowableQualifiersList>
			<AllowableQualifier>
				<QualifierReferredTo>
					<QualifierUI>Q000503</QualifierUI>
					<QualifierName>
						<String>physiopathology</String>
					</QualifierName>
				</QualifierReferredTo>
				<Abbreviation>PP</Abbreviation>
			</AllowableQualifier>
			<AllowableQualifier>
				<QualifierReferredTo>
					<QualifierUI>Q000530</QualifierUI>
					<QualifierName>
						<String>radiography</String>
					</QualifierName>
				</QualifierReferredTo>
				<Abbreviation>RA</Abbreviation>
			</AllowableQualifier>
			<AllowableQualifier>
				<QualifierReferredTo>
					<QualifierUI>Q000517</QualifierUI>
					<QualifierName>
						<String>prevention &amp; control</String>
					</QualifierName>
				</QualifierReferredTo>
				<Abbreviation>PC</Abbreviation>
			</AllowableQualifier>
			<AllowableQualifier>
				<QualifierReferredTo>
					<QualifierUI>Q000139</QualifierUI>
					<QualifierName>
						<String>chemically induced</String>
					</QualifierName>
				</QualifierReferredTo>
				<Abbreviation>CI</Abbreviation>
			</AllowableQualifier>
			<AllowableQualifier>
				<QualifierReferredTo>
					<QualifierUI>Q000151</QualifierUI>
					<QualifierName>
						<String>congenital</String>
					</QualifierName>
				</QualifierReferredTo>
				<Abbreviation>CN</Abbreviation>
			</AllowableQualifier>
			<AllowableQualifier>
				<QualifierReferredTo>
					<QualifierUI>Q000178</QualifierUI>
					<QualifierName>
						<String>diet therapy</String>
					</QualifierName>
				</QualifierReferredTo>
				<Abbreviation>DH</Abbreviation>
			</AllowableQualifier>
		</AllowableQualifiersList>
		<TreeNumberList>
			<TreeNumber>C04.588.033</TreeNumber>
		</TreeNumberList>
		<RecordOriginatorsList>
			<RecordOriginator>nlm</RecordOriginator>
			<RecordMaintainer>keveric</RecordMaintainer>
			<RecordAuthorizer>pls</RecordAuthorizer>
		</RecordOriginatorsList>
		<ConceptList>
			<Concept PreferredConceptYN="Y">
				<ConceptUI>M0000008</ConceptUI>
				<ConceptName>
					<String>Abdominal Neoplasms</String>
				</ConceptName>
				<SemanticTypeList>
					<SemanticType>
						<SemanticTypeUI>T191</SemanticTypeUI>
						<SemanticTypeName>Neoplastic Process</SemanticTypeName>
					</SemanticType>
				</SemanticTypeList>
				<TermList>
					<Term ConceptPreferredTermYN="Y" IsPermutedTermYN="N" LexicalTag="NON" PrintFlagYN="Y" RecordPreferredTermYN="Y">
						<TermUI>T000016</TermUI>
						<String>Abdominal Neoplasms</String>
						<DateCreated>
							<Year>1999</Year>
							<Month>01</Month>
							<Day>01</Day>
						</DateCreated>
						<EntryVersion>ABDOMINAL NEOPL</EntryVersion>
						<ThesaurusIDlist>
							<ThesaurusID>NLM (1966)</ThesaurusID>
						</ThesaurusIDlist>
					</Term>
					<Term ConceptPreferredTermYN="N" IsPermutedTermYN="Y" LexicalTag="NON" PrintFlagYN="N" RecordPreferredTermYN="N">
						<TermUI>T000016</TermUI>
						<String>Abdominal Neoplasm</String>
					</Term>
					<Term ConceptPreferredTermYN="N" IsPermutedTermYN="Y" LexicalTag="NON" PrintFlagYN="N" RecordPreferredTermYN="N">
						<TermUI>T000016</TermUI>
						<String>Neoplasm, Abdominal</String>
					</Term>
					<Term ConceptPreferredTermYN="N" IsPermutedTermYN="Y" LexicalTag="NON" PrintFlagYN="N" RecordPreferredTermYN="N">
						<TermUI>T000016</TermUI>
						<String>Neoplasms, Abdominal</String>
					</Term>
				</TermList>
			</Concept>
		</ConceptList>
	</DescriptorRecord>
	<DescriptorRecord DescriptorClass="1">
		<DescriptorUI>D000013</DescriptorUI>
		<DescriptorName>
			<String>Congenital Abnormalities</String>
		</DescriptorName>
		<DateCreated>
			<Year>1999</Year>
			<Month>01</Month>
			<Day>01</Day>
		</DateCreated>
		<DateRevised>
			<Year>2007</Year>
			<Month>07</Month>
			<Day>09</Day>
		</DateRevised>
		<ActiveMeSHYearList>
			<Year>2008</Year>
			<Year>2009</Year>
			<Year>2010</Year>
			<Year>2011</Year>
			<Year>2012</Year>
			<Year>2013</Year>
			<Year>2014</Year>
			<Year>2015</Year>
		</ActiveMeSHYearList>
		<AllowableQualifiersList>
			<AllowableQualifier>
				<QualifierReferredTo>
					<QualifierUI>Q000503</QualifierUI>
					<QualifierName>
						<String>physiopathology</String>
					</QualifierName>
				</QualifierReferredTo>
				<Abbreviation>PP</Abbreviation>
			</AllowableQualifier>
			<AllowableQualifier>
				<QualifierReferredTo>
					<QualifierUI>Q000097</QualifierUI>
					<QualifierName>
						<String>blood</String>
					</QualifierName>
				</QualifierReferredTo>
				<Abbreviation>BL</Abbreviation>
			</AllowableQualifier>
			<AllowableQualifier>
				<QualifierReferredTo>
					<QualifierUI>Q000134</QualifierUI>
					<QualifierName>
						<String>cerebrospinal fluid</String>
					</QualifierName>
				</QualifierReferredTo>
				<Abbreviation>CF</Abbreviation>
			</AllowableQualifier>
			<AllowableQualifier>
				<QualifierReferredTo>
					<QualifierUI>Q000178</QualifierUI>
					<QualifierName>
						<String>diet therapy</String>
					</QualifierName>
				</QualifierReferredTo>
				<Abbreviation>DH</Abbreviation>
			</AllowableQualifier>
			<AllowableQualifier>
				<QualifierReferredTo>
					<QualifierUI>Q000628</QualifierUI>
					<QualifierName>
						<String>therapy</String>
					</QualifierName>
				</QualifierReferredTo>
				<Abbreviation>TH</Abbreviation>
			</AllowableQualifier>
			<AllowableQualifier>
				<QualifierReferredTo>
					<QualifierUI>Q000523</QualifierUI>
					<QualifierName>
						<String>psychology</String>
					</QualifierName>
				</QualifierReferredTo>
				<Abbreviation>PX</Abbreviation>
			</AllowableQualifier>
		</AllowableQualifiersList>
		<HistoryNote>2008 (1963)
  </HistoryNote>
		<PublicMeSHNote>2008; see ABNORMALITIES 1963-2007
  </PublicMeSHNote>
		<EntryCombinationList>
			<EntryCombination>
				<ECIN>
					<DescriptorReferredTo>
						<DescriptorUI>D000013</DescriptorUI>
						<DescriptorName>
							<String>Congenital Abnormalities</String>
						</DescriptorName>
					</DescriptorReferredTo>
					<QualifierReferredTo>
						<QualifierUI>Q000139</QualifierUI>
						<QualifierName>
							<String>chemically induced</String>
						</QualifierName>
					</QualifierReferredTo>
				</ECIN>
				<ECOUT>
					<DescriptorReferredTo>
						<DescriptorUI>D000014</DescriptorUI>
						<DescriptorName>
							<String>Abnormalities, Drug-Induced</String>
						</DescriptorName>
					</DescriptorReferredTo>
				</ECOUT>
			</EntryCombination>
		</EntryCombinationList>
		<TreeNumberList>
			<TreeNumber>C16.131</TreeNumber>
		</TreeNumberList>
		<RecordOriginatorsList>
			<RecordOriginator>nlm</RecordOriginator>
			<RecordMaintainer>tangl</RecordMaintainer>
			<RecordAuthorizer>nelsons</RecordAuthorizer>
		</RecordOriginatorsList>
		<ConceptList>
			<Concept PreferredConceptYN="Y">
				<ConceptUI>M0000013</ConceptUI>
				<ConceptName>
					<String>Congenital Abnormalities</String>
				</ConceptName>
				<ScopeNote>Malformations of organs or body parts during development in utero.
    </ScopeNote>
				<SemanticTypeList>
					<SemanticType>
						<SemanticTypeUI>T019</SemanticTypeUI>
						<SemanticTypeName>Congenital Abnormality</SemanticTypeName>
					</SemanticType>
				</SemanticTypeList>
				<TermList>
					<Term ConceptPreferredTermYN="Y" IsPermutedTermYN="N" LexicalTag="NON" PrintFlagYN="Y" RecordPreferredTermYN="Y">
						<TermUI>T000029</TermUI>
						<String>Congenital Abnormalities</String>
						<DateCreated>
							<Year>1978</Year>
							<Month>12</Month>
							<Day>18</Day>
						</DateCreated>
						<EntryVersion>CONGEN ABNORM</EntryVersion>
						<ThesaurusIDlist>
							<ThesaurusID>NLM (1980)</ThesaurusID>
						</ThesaurusIDlist>
					</Term>
					<Term ConceptPreferredTermYN="N" IsPermutedTermYN="Y" LexicalTag="NON" PrintFlagYN="N" RecordPreferredTermYN="N">
						<TermUI>T000029</TermUI>
						<String>Abnormality, Congenital</String>
					</Term>
					<Term ConceptPreferredTermYN="N" IsPermutedTermYN="Y" LexicalTag="NON" PrintFlagYN="N" RecordPreferredTermYN="N">
						<TermUI>T000029</TermUI>
						<String>Congenital Abnormality</String>
					</Term>
					<Term ConceptPreferredTermYN="N" IsPermutedTermYN="N" LexicalTag="NON" PrintFlagYN="Y" RecordPreferredTermYN="N">
						<TermUI>T000032</TermUI>
						<String>Deformities</String>
						<DateCreated>
							<Year>1974</Year>
							<Month>03</Month>
							<Day>29</Day>
						</DateCreated>
						<ThesaurusIDlist>
							<ThesaurusID>UNK (19XX)</ThesaurusID>
						</ThesaurusIDlist>
					</Term>
					<Term ConceptPreferredTermYN="N" IsPermutedTermYN="Y" LexicalTag="NON" PrintFlagYN="N" RecordPreferredTermYN="N">
						<TermUI>T000032</TermUI>
						<String>Deformity</String>
					</Term>
					<Term ConceptPreferredTermYN="N" IsPermutedTermYN="N" LexicalTag="NON" PrintFlagYN="Y" RecordPreferredTermYN="N">
						<TermUI>T000031</TermUI>
						<String>Congenital Defects</String>
						<DateCreated>
							<Year>1977</Year>
							<Month>03</Month>
							<Day>22</Day>
						</DateCreated>
						<EntryVersion>CONGEN DEFECTS</EntryVersion>
						<ThesaurusIDlist>
							<ThesaurusID>UNK (19XX)</ThesaurusID>
						</ThesaurusIDlist>
					</Term>
					<Term ConceptPreferredTermYN="N" IsPermutedTermYN="Y" LexicalTag="NON" PrintFlagYN="N" RecordPreferredTermYN="N">
						<TermUI>T000031</TermUI>
						<String>Congenital Defect</String>
					</Term>
					<Term ConceptPreferredTermYN="N" IsPermutedTermYN="Y" LexicalTag="NON" PrintFlagYN="N" RecordPreferredTermYN="N">
						<TermUI>T000031</TermUI>
						<String>Defect, Congenital</String>
					</Term>
					<Term ConceptPreferredTermYN="N" IsPermutedTermYN="N" LexicalTag="NON" PrintFlagYN="N" RecordPreferredTermYN="N">
						<TermUI>T000030</TermUI>
						<String>Defects, Congenital</String>
						<DateCreated>
							<Year>1977</Year>
							<Month>03</Month>
							<Day>22</Day>
						</DateCreated>
						<EntryVersion>DEFECTS CONGEN</EntryVersion>
						<ThesaurusIDlist>
							<ThesaurusID>UNK (19XX)</ThesaurusID>
						</ThesaurusIDlist>
					</Term>
					<Term ConceptPreferredTermYN="N" IsPermutedTermYN="N" LexicalTag="NON" PrintFlagYN="N" RecordPreferredTermYN="N">
						<TermUI>T000028</TermUI>
						<String>Abnormalities, Congenital</String>
						<DateCreated>
							<Year>1978</Year>
							<Month>12</Month>
							<Day>18</Day>
						</DateCreated>
						<EntryVersion>ABNORM CONGEN</EntryVersion>
						<ThesaurusIDlist>
							<ThesaurusID>UNK (19XX)</ThesaurusID>
						</ThesaurusIDlist>
					</Term>
					<Term ConceptPreferredTermYN="N" IsPermutedTermYN="N" LexicalTag="NON" PrintFlagYN="Y" RecordPreferredTermYN="N">
						<TermUI>T000027</TermUI>
						<String>Birth Defects</String>
						<DateCreated>
							<Year>1976</Year>
							<Month>05</Month>
							<Day>08</Day>
						</DateCreated>
						<ThesaurusIDlist>
							<ThesaurusID>UNK (19XX)</ThesaurusID>
						</ThesaurusIDlist>
					</Term>
					<Term ConceptPreferredTermYN="N" IsPermutedTermYN="Y" LexicalTag="NON" PrintFlagYN="N" RecordPreferredTermYN="N">
						<TermUI>T000027</TermUI>
						<String>Birth Defect</String>
					</Term>
					<Term ConceptPreferredTermYN="N" IsPermutedTermYN="Y" LexicalTag="NON" PrintFlagYN="N" RecordPreferredTermYN="N">
						<TermUI>T000027</TermUI>
						<String>Defect, Birth</String>
					</Term>
					<Term ConceptPreferredTermYN="N" IsPermutedTermYN="Y" LexicalTag="NON" PrintFlagYN="N" RecordPreferredTermYN="N">
						<TermUI>T000027</TermUI>
						<String>Defects, Birth</String>
					</Term>
				</TermList>
			</Concept>
		</ConceptList>
	</DescriptorRecord>
	<DescriptorRecord DescriptorClass="1">
		<DescriptorUI>D000014</DescriptorUI>
		<DescriptorName>
			<String>Abnormalities, Drug-Induced</String>
		</DescriptorName>
		<DateCreated>
			<Year>1999</Year>
			<Month>01</Month>
			<Day>01</Day>
		</DateCreated>
		<DateRevised>
			<Year>2013</Year>
			<Month>07</Month>
			<Day>08</Day>
		</DateRevised>
		<DateEstablished>
			<Year>1964</Year>
			<Month>01</Month>
			<Day>01</Day>
		</DateEstablished>
		<ActiveMeSHYearList>
			<Year>2014</Year>
			<Year>2015</Year>
		</ActiveMeSHYearList>
		<AllowableQualifiersList>
			<AllowableQualifier>
				<QualifierReferredTo>
					<QualifierUI>Q000503</QualifierUI>
					<QualifierName>
						<String>physiopathology</String>
					</QualifierName>
				</QualifierReferredTo>
				<Abbreviation>PP</Abbreviation>
			</AllowableQualifier>
			<AllowableQualifier>
				<QualifierReferredTo>
					<QualifierUI>Q000530</QualifierUI>
					<QualifierName>
						<String>radiography</String>
					</QualifierName>
				</QualifierReferredTo>
				<Abbreviation>RA</Abbreviation>
			</AllowableQualifier>
			<AllowableQualifier>
				<QualifierReferredTo>
					<QualifierUI>Q000517</QualifierUI>
					<QualifierName>
						<String>prevention &amp; control</String>
					</QualifierName>
				</QualifierReferredTo>
				<Abbreviation>PC</Abbreviation>
			</AllowableQualifier>
			<AllowableQualifier>
				<QualifierReferredTo>
					<QualifierUI>Q000097</QualifierUI>
					<QualifierName>
						<String>blood</String>
					</QualifierName>
				</QualifierReferredTo>
				<Abbreviation>BL</Abbreviation>
			</AllowableQualifier>
		</AllowableQualifiersList>
		<HistoryNote>64
  </HistoryNote>
		<PublicMeSHNote>64
  </PublicMeSHNote>
		<SeeRelatedList>
			<SeeRelatedDescriptor>
				<DescriptorReferredTo>
					<DescriptorUI>D013723</DescriptorUI>
					<DescriptorName>
						<String>Teratogens</String>
					</DescriptorName>
				</DescriptorReferredTo>
			</SeeRelatedDescriptor>
			<SeeRelatedDescriptor>
				<DescriptorReferredTo>
					<DescriptorUI>D064793</DescriptorUI>
					<DescriptorName>
						<String>Teratogenesis</String>
					</DescriptorName>
				</DescriptorReferredTo>
			</SeeRelatedDescriptor>
		</SeeRelatedList>
		<TreeNumberList>
			<TreeNumber>C16.131.042</TreeNumber>
		</TreeNumberList>
		<RecordOriginatorsList>
			<RecordOriginator>nlm</RecordOriginator>
			<RecordMaintainer>schulmaj</RecordMaintainer>
			<RecordAuthorizer>kilbourj</RecordAuthorizer>
		</RecordOriginatorsList>
		<ConceptList>
			<Concept PreferredConceptYN="Y">
				<ConceptUI>M0000014</ConceptUI>
				<ConceptName>
					<String>Abnormalities, Drug-Induced</String>
				</ConceptName>
				<ScopeNote>Congenital abnormalities caused by medicinal substances or drugs of abuse given to or taken by the mother, or to which she is inadvertently exposed during the manufacture of such substances. The concept excludes abnormalities resulting from exposure to non-medicinal chemicals in the environment.
    </ScopeNote>
				<SemanticTypeList>
					<SemanticType>
						<SemanticTypeUI>T019</SemanticTypeUI>
						<SemanticTypeName>Congenital Abnormality</SemanticTypeName>
					</SemanticType>
				</SemanticTypeList>
				<TermList>
					<Term ConceptPreferredTermYN="Y" IsPermutedTermYN="N" LexicalTag="NON" PrintFlagYN="Y" RecordPreferredTermYN="Y">
						<TermUI>T000034</TermUI>
						<String>Abnormalities, Drug-Induced</String>
						<DateCreated>
							<Year>1999</Year>
							<Month>01</Month>
							<Day>01</Day>
						</DateCreated>
						<EntryVersion>ABNORM DRUG IND</EntryVersion>
						<ThesaurusIDlist>
							<ThesaurusID>NLM (1964)</ThesaurusID>
						</ThesaurusIDlist>
					</Term>
					<Term ConceptPreferredTermYN="N" IsPermutedTermYN="Y" LexicalTag="NON" PrintFlagYN="N" RecordPreferredTermYN="N">
						<TermUI>T000034</TermUI>
						<String>Abnormalities, Drug Induced</String>
					</Term>
					<Term ConceptPreferredTermYN="N" IsPermutedTermYN="N" LexicalTag="NON" PrintFlagYN="N" RecordPreferredTermYN="N">
						<TermUI>T000033</TermUI>
						<String>Drug-Induced Abnormalities</String>
						<DateCreated>
							<Year>1977</Year>
							<Month>12</Month>
							<Day>07</Day>
						</DateCreated>
						<EntryVersion>DRUG IND ABNORM</EntryVersion>
						<ThesaurusIDlist>
							<ThesaurusID>UNK (19XX)</ThesaurusID>
						</ThesaurusIDlist>
					</Term>
					<Term ConceptPreferredTermYN="N" IsPermutedTermYN="Y" LexicalTag="NON" PrintFlagYN="N" RecordPreferredTermYN="N">
						<TermUI>T000033</TermUI>
						<String>Abnormality, Drug-Induced</String>
					</Term>
					<Term ConceptPreferredTermYN="N" IsPermutedTermYN="Y" LexicalTag="NON" PrintFlagYN="N" RecordPreferredTermYN="N">
						<TermUI>T000033</TermUI>
						<String>Drug Induced Abnormalities</String>
					</Term>
					<Term ConceptPreferredTermYN="N" IsPermutedTermYN="Y" LexicalTag="NON" PrintFlagYN="N" RecordPreferredTermYN="N">
						<TermUI>T000033</TermUI>
						<String>Drug-Induced Abnormality</String>
					</Term>
				</TermList>
			</Concept>
		</ConceptList>
	</DescriptorRecord>
	<DescriptorRecord DescriptorClass="1">
		<DescriptorUI>D000015</DescriptorUI>
		<DescriptorName>
			<String>Abnormalities, Multiple</String>
		</DescriptorName>
		<DateCreated>
			<Year>1999</Year>
			<Month>01</Month>
			<Day>01</Day>
		</DateCreated>
		<DateRevised>
			<Year>2011</Year>
			<Month>07</Month>
			<Day>05</Day>
		</DateRevised>
		<DateEstablished>
			<Year>1968</Year>
			<Month>01</Month>
			<Day>01</Day>
		</DateEstablished>
		<ActiveMeSHYearList>
			<Year>2012</Year>
			<Year>2013</Year>
			<Year>2014</Year>
			<Year>2015</Year>
		</ActiveMeSHYearList>
		<AllowableQualifiersList>
			<AllowableQualifier>
				<QualifierReferredTo>
					<QualifierUI>Q000503</QualifierUI>
					<QualifierName>
						<String>physiopathology</String>
					</QualifierName>
				</QualifierReferredTo>
				<Abbreviation>PP</Abbreviation>
			</AllowableQualifier>
			<AllowableQualifier>
				<QualifierReferredTo>
					<QualifierUI>Q000134</QualifierUI>
					<QualifierName>
						<String>cerebrospinal fluid</String>
					</QualifierName>
				</QualifierReferredTo>
				<Abbreviation>CF</Abbreviation>
			</AllowableQualifier>
			<AllowableQualifier>
				<QualifierReferredTo>
					<QualifierUI>Q000139</QualifierUI>
					<QualifierName>
						<String>chemically induced</String>
					</QualifierName>
				</QualifierReferredTo>
				<Abbreviation>CI</Abbreviation>
			</AllowableQualifier>
			<AllowableQualifier>
				<QualifierReferredTo>
					<QualifierUI>Q000191</QualifierUI>
					<QualifierName>
						<String>economics</String>
					</QualifierName>
				</QualifierReferredTo>
				<Abbreviation>EC</Abbreviation>
			</AllowableQualifier>
		</AllowableQualifiersList>
		<HistoryNote>68
  </HistoryNote>
		<PublicMeSHNote>68
  </PublicMeSHNote>
		<PreviousIndexingList>
			<PreviousIndexing>Abnormalities (1966-1967)</PreviousIndexing>
		</PreviousIndexingList>
		<SeeRelatedList>
			<SeeRelatedDescriptor>
				<DescriptorReferredTo>
					<DescriptorUI>D008607</DescriptorUI>
					<DescriptorName>
						<String>Intellectual Disability</String>
					</DescriptorName>
				</DescriptorReferredTo>
			</SeeRelatedDescriptor>
		</SeeRelatedList>
		<TreeNumberList>
			<TreeNumber>C16.131.077</TreeNumber>
		</TreeNumberList>
		<RecordOriginatorsList>
			<RecordOriginator>nlm</RecordOriginator>
			<RecordMaintainer>nlm</RecordMaintainer>
			<RecordAuthorizer>nlm</RecordAuthorizer>
		</RecordOriginatorsList>
		<ConceptList>
			<Concept PreferredConceptYN="Y">
				<ConceptUI>M0000015</ConceptUI>
				<ConceptName>
					<String>Abnormalities, Multiple</String>
				</ConceptName>
				<SemanticTypeList>
					<SemanticType>
						<SemanticTypeUI>T019</SemanticTypeUI>
						<SemanticTypeName>Congenital Abnormality</SemanticTypeName>
					</SemanticType>
				</SemanticTypeList>
				<TermList>
					<Term ConceptPreferredTermYN="Y" IsPermutedTermYN="N" LexicalTag="NON" PrintFlagYN="Y" RecordPreferredTermYN="Y">
						<TermUI>T000036</TermUI>
						<String>Abnormalities, Multiple</String>
						<DateCreated>
							<Year>1999</Year>
							<Month>01</Month>
							<Day>01</Day>
						</DateCreated>
						<EntryVersion>ABNORM MULTIPLE</EntryVersion>
						<ThesaurusIDlist>
							<ThesaurusID>NLM (1968)</ThesaurusID>
						</ThesaurusIDlist>
					</Term>
					<Term ConceptPreferredTermYN="N" IsPermutedTermYN="N" LexicalTag="NON" PrintFlagYN="N" RecordPreferredTermYN="N">
						<TermUI>T000035</TermUI>
						<String>Multiple Abnormalities</String>
						<DateCreated>
							<Year>1986</Year>
							<Month>01</Month>
							<Day>01</Day>
						</DateCreated>
						<EntryVersion>MULTIPLE ABNORM</EntryVersion>
						<ThesaurusIDlist>
							<ThesaurusID>UNK (19XX)</ThesaurusID>
						</ThesaurusIDlist>
					</Term>
				</TermList>
			</Concept>
		</ConceptList>
	</DescriptorRecord>
	<DescriptorRecord DescriptorClass="1">
		<DescriptorUI>D000016</DescriptorUI>
		<DescriptorName>
			<String>Abnormalities, Radiation-Induced</String>
		</DescriptorName>
		<DateCreated>
			<Year>1978</Year>
			<Month>03</Month>
			<Day>20</Day>
		</DateCreated>
		<DateRevised>
			<Year>2013</Year>
			<Month>07</Month>
			<Day>08</Day>
		</DateRevised>
		<DateEstablished>
			<Year>1979</Year>
			<Month>01</Month>
			<Day>01</Day>
		</DateEstablished>
		<ActiveMeSHYearList>
			<Year>2014</Year>
			<Year>2015</Year>
		</ActiveMeSHYearList>
		<AllowableQualifiersList>
			<AllowableQualifier>
				<QualifierReferredTo>
					<QualifierUI>Q000503</QualifierUI>
					<QualifierName>
						<String>physiopathology</String>
					</QualifierName>
				</QualifierReferredTo>
				<Abbreviation>PP</Abbreviation>
			</AllowableQualifier>
			<AllowableQualifier>
				<QualifierReferredTo>
					<QualifierUI>Q000097</QualifierUI>
					<QualifierName>
						<String>blood</String>
					</QualifierName>
				</QualifierReferredTo>
				<Abbreviation>BL</Abbreviation>
			</AllowableQualifier>
			<AllowableQualifier>
				<QualifierReferredTo>
					<QualifierUI>Q000134</QualifierUI>
					<QualifierName>
						<String>cerebrospinal fluid</String>
					</QualifierName>
				</QualifierReferredTo>
				<Abbreviation>CF</Abbreviation>
			</AllowableQualifier>
		</AllowableQualifiersList>
		<HistoryNote>79
  </HistoryNote>
		<PublicMeSHNote>79
  </PublicMeSHNote>
		<PreviousIndexingList>
			<PreviousIndexing>Abnormalities (1966-1978)</PreviousIndexing>
			<PreviousIndexing>Radiation Injuries (1966-1978)</PreviousIndexing>
		</PreviousIndexingList>
		<SeeRelatedList>
			<SeeRelatedDescriptor>
				<DescriptorReferredTo>
					<DescriptorUI>D064793</DescriptorUI>
					<DescriptorName>
						<String>Teratogenesis</String>
					</DescriptorName>
				</DescriptorReferredTo>
			</SeeRelatedDescriptor>
		</SeeRelatedList>
		<TreeNumberList>
			<TreeNumber>C16.131.080</TreeNumber>
			<TreeNumber>C26.733.031</TreeNumber>
			<TreeNumber>N06.850.810.300.360.031</TreeNumber>
		</TreeNumberList>
		<RecordOriginatorsList>
			<RecordOriginator>aep</RecordOriginator>
			<RecordMaintainer>schulmaj</RecordMaintainer>
			<RecordAuthorizer>kilbourj</RecordAuthorizer>
		</RecordOriginatorsList>
		<ConceptList>
			<Concept PreferredConceptYN="Y">
				<ConceptUI>M0000016</ConceptUI>
				<ConceptName>
					<String>Abnormalities, Radiation-Induced</String>
				</ConceptName>
				<ScopeNote>Congenital changes in the morphology of organs produced by exposure to ionizing or non-ionizing radiation.
    </ScopeNote>
				<SemanticTypeList>
					<SemanticType>
						<SemanticTypeUI>T019</SemanticTypeUI>
						<SemanticTypeName>Congenital Abnormality</SemanticTypeName>
					</SemanticType>
				</SemanticTypeList>
				<TermList>
					<Term ConceptPreferredTermYN="Y" IsPermutedTermYN="N" LexicalTag="NON" PrintFlagYN="Y" RecordPreferredTermYN="Y">
						<TermUI>T000038</TermUI>
						<String>Abnormalities, Radiation-Induced</String>
						<DateCreated>
							<Year>1999</Year>
							<Month>01</Month>
							<Day>01</Day>
						</DateCreated>
						<EntryVersion>ABNORM RAD IND</EntryVersion>
						<ThesaurusIDlist>
							<ThesaurusID>NLM (1979)</ThesaurusID>
						</ThesaurusIDlist>
					</Term>
					<Term ConceptPreferredTermYN="N" IsPermutedTermYN="Y" LexicalTag="NON" PrintFlagYN="N" RecordPreferredTermYN="N">
						<TermUI>T000038</TermUI>
						<String>Abnormalities, Radiation Induced</String>
					</Term>
					<Term ConceptPreferredTermYN="N" IsPermutedTermYN="N" LexicalTag="NON" PrintFlagYN="N" RecordPreferredTermYN="N">
						<TermUI>T000037</TermUI>
						<String>Radiation-Induced Abnormalities</String>
						<DateCreated>
							<Year>1978</Year>
							<Month>03</Month>
							<Day>20</Day>
						</DateCreated>
						<EntryVersion>RAD IND ABNORM</EntryVersion>
						<ThesaurusIDlist>
							<ThesaurusID>UNK (19XX)</ThesaurusID>
						</ThesaurusIDlist>
					</Term>
					<Term ConceptPreferredTermYN="N" IsPermutedTermYN="Y" LexicalTag="NON" PrintFlagYN="N" RecordPreferredTermYN="N">
						<TermUI>T000037</TermUI>
						<String>Abnormality, Radiation-Induced</String>
					</Term>
					<Term ConceptPreferredTermYN="N" IsPermutedTermYN="Y" LexicalTag="NON" PrintFlagYN="N" RecordPreferredTermYN="N">
						<TermUI>T000037</TermUI>
						<String>Radiation Induced Abnormalities</String>
					</Term>
					<Term ConceptPreferredTermYN="N" IsPermutedTermYN="Y" LexicalTag="NON" PrintFlagYN="N" RecordPreferredTermYN="N">
						<TermUI>T000037</TermUI>
						<String>Radiation-Induced Abnormality</String>
					</Term>
				</TermList>
			</Concept>
		</ConceptList>
	</DescriptorRecord>
	<DescriptorRecord DescriptorClass="1">
		<DescriptorUI>D000022</DescriptorUI>
		<DescriptorName>
			<String>Abortion, Spontaneous</String>
		</DescriptorName>
		<DateCreated>
			<Year>1999</Year>
			<Month>01</Month>
			<Day>01</Day>
		</DateCreated>
		<DateRevised>
			<Year>2005</Year>
			<Month>06</Month>
			<Day>30</Day>
		</DateRevised>
		<ActiveMeSHYearList>
			<Year>2006</Year>
			<Year>2007</Year>
			<Year>2008</Year>
			<Year>2009</Year>
			<Year>2010</Year>
			<Year>2011</Year>
			<Year>2012</Year>
			<Year>2013</Year>
			<Year>2014</Year>
			<Year>2015</Year>
		</ActiveMeSHYearList>
		<AllowableQualifiersList>
			<AllowableQualifier>
				<QualifierReferredTo>
					<QualifierUI>Q000134</QualifierUI>
					<QualifierName>
						<String>cerebrospinal fluid</String>
					</QualifierName>
				</QualifierReferredTo>
				<Abbreviation>CF</Abbreviation>
			</AllowableQualifier>
			<AllowableQualifier>
				<QualifierReferredTo>
					<QualifierUI>Q000139</QualifierUI>
					<QualifierName>
						<String>chemically induced</String>
					</QualifierName>
				</QualifierReferredTo>
				<Abbreviation>CI</Abbreviation>
			</AllowableQualifier>
		</AllowableQualifiersList>
		<HistoryNote>99(63)
  </HistoryNote>
		<PublicMeSHNote>99; see ABORTION 1966-98; for ABORTION, SPONTANEOUS see ABORTION 1992-98
  </PublicMeSHNote>
		<EntryCombinationList>
			<EntryCombination>
				<ECIN>
					<DescriptorReferredTo>
						<DescriptorUI>D000022</DescriptorUI>
						<DescriptorName>
							<String>Abortion, Spontaneous</String>
						</DescriptorName>
					</DescriptorReferredTo>
					<QualifierReferredTo>
						<QualifierUI>Q000662</QualifierUI>
						<QualifierName>
							<String>veterinary</String>
						</QualifierName>
					</QualifierReferredTo>
				</ECIN>
				<ECOUT>
					<DescriptorReferredTo>
						<DescriptorUI>D000034</DescriptorUI>
						<DescriptorName>
							<String>Abortion, Veterinary</String>
						</DescriptorName>
					</DescriptorReferredTo>
				</ECOUT>
			</EntryCombination>
		</EntryCombinationList>
		<SeeRelatedList>
			<SeeRelatedDescriptor>
				<DescriptorReferredTo>
					<DescriptorUI>D000019</DescriptorUI>
					<DescriptorName>
						<String>Abortifacient Agents</String>
					</DescriptorName>
				</DescriptorReferredTo>
			</SeeRelatedDescriptor>
			<SeeRelatedDescriptor>
				<DescriptorReferredTo>
					<DescriptorUI>D037881</DescriptorUI>
					<DescriptorName>
						<String>Aborted Fetus</String>
					</DescriptorName>
				</DescriptorReferredTo>
			</SeeRelatedDescriptor>
		</SeeRelatedList>
		<TreeNumberList>
			<TreeNumber>C13.703.039</TreeNumber>
		</TreeNumberList>
		<RecordOriginatorsList>
			<RecordOriginator>nlm</RecordOriginator>
			<RecordMaintainer>tangl</RecordMaintainer>
			<RecordAuthorizer>nelsons</RecordAuthorizer>
		</RecordOriginatorsList>
		<ConceptList>
			<Concept PreferredConceptYN="Y">
				<ConceptUI>M0000024</ConceptUI>
				<ConceptName>
					<String>Abortion, Spontaneous</String>
				</ConceptName>
				<ScopeNote>Expulsion of the product of FERTILIZATION before completing the term of GESTATION and without deliberate interference.
    </ScopeNote>
				<SemanticTypeList>
					<SemanticType>
						<SemanticTypeUI>T047</SemanticTypeUI>
						<SemanticTypeName>Disease or Syndrome</SemanticTypeName>
					</SemanticType>
				</SemanticTypeList>
				<ConceptRelationList>
					<ConceptRelation RelationName="NRW">
						<Concept1UI>M0000024</Concept1UI>
						<Concept2UI>M0000025</Concept2UI>
					</ConceptRelation>
				</ConceptRelationList>
				<TermList>
					<Term ConceptPreferredTermYN="Y" IsPermutedTermYN="N" LexicalTag="NON" PrintFlagYN="Y" RecordPreferredTermYN="Y">
						<TermUI>T000053</TermUI>
						<String>Abortion, Spontaneous</String>
						<DateCreated>
							<Year>1999</Year>
							<Month>01</Month>
							<Day>01</Day>
						</DateCreated>
						<ThesaurusIDlist>
							<ThesaurusID>NLM (1999)</ThesaurusID>
						</ThesaurusIDlist>
					</Term>
					<Term ConceptPreferredTermYN="N" IsPermutedTermYN="Y" LexicalTag="NON" PrintFlagYN="N" RecordPreferredTermYN="N">
						<TermUI>T000053</TermUI>
						<String>Abortions, Spontaneous</String>
					</Term>
					<Term ConceptPreferredTermYN="N" IsPermutedTermYN="Y" LexicalTag="NON" PrintFlagYN="N" RecordPreferredTermYN="N">
						<TermUI>T000053</TermUI>
						<String>Spontaneous Abortions</String>
					</Term>
					<Term ConceptPreferredTermYN="N" IsPermutedTermYN="N" LexicalTag="NON" PrintFlagYN="Y" RecordPreferredTermYN="N">
						<TermUI>T000054</TermUI>
						<String>Miscarriage</String>
						<DateCreated>
							<Year>1974</Year>
							<Month>03</Month>
							<Day>29</Day>
						</DateCreated>
						<ThesaurusIDlist>
							<ThesaurusID>UNK (19XX)</ThesaurusID>
						</ThesaurusIDlist>
					</Term>
					<Term ConceptPreferredTermYN="N" IsPermutedTermYN="Y" LexicalTag="NON" PrintFlagYN="N" RecordPreferredTermYN="N">
						<TermUI>T000054</TermUI>
						<String>Miscarriages</String>
					</Term>
					<Term ConceptPreferredTermYN="N" IsPermutedTermYN="N" LexicalTag="NON" PrintFlagYN="N" RecordPreferredTermYN="N">
						<TermUI>T484312</TermUI>
						<String>Spontaneous Abortion</String>
						<DateCreated>
							<Year>2002</Year>
							<Month>03</Month>
							<Day>04</Day>
						</DateCreated>
						<ThesaurusIDlist>
							<ThesaurusID>NLM (2003)</ThesaurusID>
						</ThesaurusIDlist>
					</Term>
				</TermList>
			</Concept>
			<Concept PreferredConceptYN="N">
				<ConceptUI>M0000025</ConceptUI>
				<ConceptName>
					<String>Abortion, Tubal</String>
				</ConceptName>
				<SemanticTypeList>
					<SemanticType>
						<SemanticTypeUI>T047</SemanticTypeUI>
						<SemanticTypeName>Disease or Syndrome</SemanticTypeName>
					</SemanticType>
				</SemanticTypeList>
				<ConceptRelationList>
					<ConceptRelation RelationName="NRW">
						<Concept1UI>M0000024</Concept1UI>
						<Concept2UI>M0000025</Concept2UI>
					</ConceptRelation>
				</ConceptRelationList>
				<TermList>
					<Term ConceptPreferredTermYN="Y" IsPermutedTermYN="N" LexicalTag="NON" PrintFlagYN="N" RecordPreferredTermYN="N">
						<TermUI>T000055</TermUI>
						<String>Abortion, Tubal</String>
						<DateCreated>
							<Year>1978</Year>
							<Month>12</Month>
							<Day>18</Day>
						</DateCreated>
						<ThesaurusIDlist>
							<ThesaurusID>NLM (1980)</ThesaurusID>
						</ThesaurusIDlist>
					</Term>
					<Term ConceptPreferredTermYN="N" IsPermutedTermYN="Y" LexicalTag="NON" PrintFlagYN="N" RecordPreferredTermYN="N">
						<TermUI>T000055</TermUI>
						<String>Abortions, Tubal</String>
					</Term>
					<Term ConceptPreferredTermYN="N" IsPermutedTermYN="Y" LexicalTag="NON" PrintFlagYN="N" RecordPreferredTermYN="N">
						<TermUI>T000055</TermUI>
						<String>Tubal Abortion</String>
					</Term>
					<Term ConceptPreferredTermYN="N" IsPermutedTermYN="Y" LexicalTag="NON" PrintFlagYN="N" RecordPreferredTermYN="N">
						<TermUI>T000055</TermUI>
						<String>Tubal Abortions</String>
					</Term>
				</TermList>
			</Concept>
		</ConceptList>
	</DescriptorRecord>
	<DescriptorRecord DescriptorClass="1">
		<DescriptorUI>D000079</DescriptorUI>
		<DescriptorName>
			<String>Acetaldehyde</String>
		</DescriptorName>
		<DateCreated>
			<Year>1999</Year>
			<Month>01</Month>
			<Day>01</Day>
		</DateCreated>
		<DateRevised>
			<Year>2013</Year>
			<Month>07</Month>
			<Day>08</Day>
		</DateRevised>
		<ActiveMeSHYearList>
			<Year>2014</Year>
			<Year>2015</Year>
		</ActiveMeSHYearList>
		<AllowableQualifiersList>
			<AllowableQualifier>
				<QualifierReferredTo>
					<QualifierUI>Q000627</QualifierUI>
					<QualifierName>
						<String>therapeutic use</String>
					</QualifierName>
				</QualifierReferredTo>
				<Abbreviation>TU</Abbreviation>
			</AllowableQualifier>
			<AllowableQualifier>
				<QualifierReferredTo>
					<QualifierUI>Q000134</QualifierUI>
					<QualifierName>
						<String>cerebrospinal fluid</String>
					</QualifierName>
				</QualifierReferredTo>
				<Abbreviation>CF</Abbreviation>
			</AllowableQualifier>
			<AllowableQualifier>
				<QualifierReferredTo>
					<QualifierUI>Q000138</QualifierUI>
					<QualifierName>
						<String>chemical synthesis</String>
					</QualifierName>
				</QualifierReferredTo>
				<Abbreviation>CS</Abbreviation>
			</AllowableQualifier>
		</AllowableQualifiersList>
		<TreeNumberList>
			<TreeNumber>D02.047.064</TreeNumber>
		</TreeNumberList>
		<RecordOriginatorsList>
			<RecordOriginator>nlm</RecordOriginator>
			<RecordMaintainer>system</RecordMaintainer>
			<RecordAuthorizer>kilbourj</RecordAuthorizer>
		</RecordOriginatorsList>
		<ConceptList>
			<Concept PreferredConceptYN="Y">
				<ConceptUI>M0000111</ConceptUI>
				<ConceptName>
					<String>Acetaldehyde</String>
				</ConceptName>
				<CASN1Name>Acetaldehyde</CASN1Name>
				<RegistryNumber>GO1N1ZPR3B</RegistryNumber>
				<ScopeNote>A colorless, flammable liquid used in the manufacture of acetic acid, perfumes, and flavors. It is also an intermediate in the metabolism of alcohol. It has a general narcotic action and also causes irritation of mucous membranes. Large doses may cause death from respiratory paralysis.
    </ScopeNote>
				<SemanticTypeList>
					<SemanticType>
						<SemanticTypeUI>T109</SemanticTypeUI>
						<SemanticTypeName>Organic Chemical</SemanticTypeName>
					</SemanticType>
				</SemanticTypeList>
				<RelatedRegistryNumberList>
					<RelatedRegistryNumber>75-07-0 (Acetaldehyde)</RelatedRegistryNumber>
				</RelatedRegistryNumberList>
				<TermList>
					<Term ConceptPreferredTermYN="Y" IsPermutedTermYN="N" LexicalTag="NON" PrintFlagYN="Y" RecordPreferredTermYN="Y">
						<TermUI>T000207</TermUI>
						<String>Acetaldehyde</String>
						<DateCreated>
							<Year>1999</Year>
							<Month>01</Month>
							<Day>01</Day>
						</DateCreated>
						<ThesaurusIDlist>
							<ThesaurusID>FDA SRS (2014)</ThesaurusID>
							<ThesaurusID>NLM (1966)</ThesaurusID>
						</ThesaurusIDlist>
					</Term>
					<Term ConceptPreferredTermYN="N" IsPermutedTermYN="N" LexicalTag="NON" PrintFlagYN="N" RecordPreferredTermYN="N">
						<TermUI>T000208</TermUI>
						<String>Ethanal</String>
						<DateCreated>
							<Year>1991</Year>
							<Month>02</Month>
							<Day>22</Day>
						</DateCreated>
						<ThesaurusIDlist>
							<ThesaurusID>FDA SRS (2014)</ThesaurusID>
							<ThesaurusID>NLM (1992)</ThesaurusID>
						</ThesaurusIDlist>
					</Term>
				</TermList>
			</Concept>
		</ConceptList>
	</DescriptorRecord>
	<DescriptorRecord DescriptorClass="1">
		<DescriptorUI>D000080</DescriptorUI>
		<DescriptorName>
			<String>Acetals</String>
		</DescriptorName>
		<DateCreated>
			<Year>1999</Year>
			<Month>01</Month>
			<Day>01</Day>
		</DateCreated>
		<DateRevised>
			<Year>1992</Year>
			<Month>05</Month>
			<Day>07</Day>
		</DateRevised>
		<DateEstablished>
			<Year>1974</Year>
			<Month>01</Month>
			<Day>01</Day>
		</DateEstablished>
		<ActiveMeSHYearList>
			<Year>1993</Year>
			<Year>1994</Year>
			<Year>1995</Year>
			<Year>1996</Year>
			<Year>1997</Year>
			<Year>1998</Year>
			<Year>1999</Year>
			<Year>2000</Year>
			<Year>2001</Year>
			<Year>2002</Year>
			<Year>2003</Year>
			<Year>2004</Year>
			<Year>2005</Year>
			<Year>2006</Year>
			<Year>2007</Year>
			<Year>2008</Year>
			<Year>2009</Year>
			<Year>2010</Year>
			<Year>2011</Year>
			<Year>2012</Year>
			<Year>2013</Year>
			<Year>2014</Year>
			<Year>2015</Year>
		</ActiveMeSHYearList>
		<AllowableQualifiersList>
			<AllowableQualifier>
				<QualifierReferredTo>
					<QualifierUI>Q000627</QualifierUI>
					<QualifierName>
						<String>therapeutic use</String>
					</QualifierName>
				</QualifierReferredTo>
				<Abbreviation>TU</Abbreviation>
			</AllowableQualifier>
			<AllowableQualifier>
				<QualifierReferredTo>
					<QualifierUI>Q000633</QualifierUI>
					<QualifierName>
						<String>toxicity</String>
					</QualifierName>
				</QualifierReferredTo>
				<Abbreviation>TO</Abbreviation>
			</AllowableQualifier>
			<AllowableQualifier>
				<QualifierReferredTo>
					<QualifierUI>Q000097</QualifierUI>
					<QualifierName>
						<String>blood</String>
					</QualifierName>
				</QualifierReferredTo>
				<Abbreviation>BL</Abbreviation>
			</AllowableQualifier>
			<AllowableQualifier>
				<QualifierReferredTo>
					<QualifierUI>Q000134</QualifierUI>
					<QualifierName>
						<String>cerebrospinal fluid</String>
					</QualifierName>
				</QualifierReferredTo>
				<Abbreviation>CF</Abbreviation>
			</AllowableQualifier>
		</AllowableQualifiersList>
		<HistoryNote>74(72)
  </HistoryNote>
		<PublicMeSHNote>74
  </PublicMeSHNote>
		<PreviousIndexingList>
			<PreviousIndexing>Ethers (1966-1971)</PreviousIndexing>
		</PreviousIndexingList>
		<TreeNumberList>
			<TreeNumber>D02.355.071</TreeNumber>
		</TreeNumberList>
		<RecordOriginatorsList>
			<RecordOriginator>nlm</RecordOriginator>
			<RecordMaintainer>tap</RecordMaintainer>
			<RecordAuthorizer>pls</RecordAuthorizer>
		</RecordOriginatorsList>
		<ConceptList>
			<Concept PreferredConceptYN="Y">
				<ConceptUI>M0000112</ConceptUI>
				<ConceptName>
					<String>Acetals</String>
				</ConceptName>
				<RegistryNumber>0</RegistryNumber>
				<SemanticTypeList>
					<SemanticType>
						<SemanticTypeUI>T109</SemanticTypeUI>
						<SemanticTypeName>Organic Chemical</SemanticTypeName>
					</SemanticType>
				</SemanticTypeList>
				<TermList>
					<Term ConceptPreferredTermYN="Y" IsPermutedTermYN="N" LexicalTag="NON" PrintFlagYN="Y" RecordPreferredTermYN="Y">
						<TermUI>T000209</TermUI>
						<String>Acetals</String>
						<DateCreated>
							<Year>1999</Year>
							<Month>01</Month>
							<Day>01</Day>
						</DateCreated>
						<ThesaurusIDlist>
							<ThesaurusID>NLM (1972)</ThesaurusID>
						</ThesaurusIDlist>
					</Term>
				</TermList>
			</Concept>
		</ConceptList>
	</DescriptorRecord>
	<DescriptorRecord DescriptorClass="1">
		<DescriptorUI>D000081</DescriptorUI>
		<DescriptorName>
			<String>Acetamides</String>
		</DescriptorName>
		<DateCreated>
			<Year>1999</Year>
			<Month>01</Month>
			<Day>01</Day>
		</DateCreated>
		<DateRevised>
			<Year>2012</Year>
			<Month>07</Month>
			<Day>03</Day>
		</DateRevised>
		<DateEstablished>
			<Year>1973</Year>
			<Month>01</Month>
			<Day>01</Day>
		</DateEstablished>
		<ActiveMeSHYearList>
			<Year>2013</Year>
			<Year>2014</Year>
			<Year>2015</Year>
		</ActiveMeSHYearList>
		<AllowableQualifiersList>
			<AllowableQualifier>
				<QualifierReferredTo>
					<QualifierUI>Q000627</QualifierUI>
					<QualifierName>
						<String>therapeutic use</String>
					</QualifierName>
				</QualifierReferredTo>
				<Abbreviation>TU</Abbreviation>
			</AllowableQualifier>
			<AllowableQualifier>
				<QualifierReferredTo>
					<QualifierUI>Q000633</QualifierUI>
					<QualifierName>
						<String>toxicity</String>
					</QualifierName>
				</QualifierReferredTo>
				<Abbreviation>TO</Abbreviation>
			</AllowableQualifier>
			<AllowableQualifier>
				<QualifierReferredTo>
					<QualifierUI>Q000134</QualifierUI>
					<QualifierName>
						<String>cerebrospinal fluid</String>
					</QualifierName>
				</QualifierReferredTo>
				<Abbreviation>CF</Abbreviation>
			</AllowableQualifier>
		</AllowableQualifiersList>
		<HistoryNote>73(71)
  </HistoryNote>
		<PublicMeSHNote>73
  </PublicMeSHNote>
		<PreviousIndexingList>
			<PreviousIndexing>Acetic Acids (1966-1970)</PreviousIndexing>
			<PreviousIndexing>Amides (1966-1970)</PreviousIndexing>
		</PreviousIndexingList>
		<TreeNumberList>
			<TreeNumber>D02.065.064</TreeNumber>
			<TreeNumber>D02.241.081.018.110</TreeNumber>
		</TreeNumberList>
		<RecordOriginatorsList>
			<RecordOriginator>nlm</RecordOriginator>
			<RecordMaintainer>pashj</RecordMaintainer>
			<RecordAuthorizer>nelsons</RecordAuthorizer>
		</RecordOriginatorsList>
		<ConceptList>
			<Concept PreferredConceptYN="Y">
				<ConceptUI>M0000113</ConceptUI>
				<ConceptName>
					<String>Acetamides</String>
				</ConceptName>
				<RegistryNumber>0</RegistryNumber>
				<ScopeNote>Derivatives of acetamide that are used as solvents, as mild irritants, and in organic synthesis.
    </ScopeNote>
				<SemanticTypeList>
					<SemanticType>
						<SemanticTypeUI>T109</SemanticTypeUI>
						<SemanticTypeName>Organic Chemical</SemanticTypeName>
					</SemanticType>
				</SemanticTypeList>
				<TermList>
					<Term ConceptPreferredTermYN="Y" IsPermutedTermYN="N" LexicalTag="NON" PrintFlagYN="Y" RecordPreferredTermYN="Y">
						<TermUI>T000210</TermUI>
						<String>Acetamides</String>
						<DateCreated>
							<Year>1999</Year>
							<Month>01</Month>
							<Day>01</Day>
						</DateCreated>
						<ThesaurusIDlist>
							<ThesaurusID>NLM (1971)</ThesaurusID>
						</ThesaurusIDlist>
					</Term>
				</TermList>
			</Concept>
		</ConceptList>
	</DescriptorRecord>
</DescriptorRecordSet>
